leanrl/__init__.py
leanrl/core/__init__.py
leanrl/core/namespaces.py
leanrl/core/parser.py
leanrl/core/streaming.py
leanrl/linkbases/README.md
leanrl/linkbases/__init__.py
leanrl/linkbases/calculation.py
leanrl/linkbases/definition.py
leanrl/linkbases/hierarchy.py
leanrl/linkbases/label.py
leanrl/linkbases/presentation.py
leanrl/linkbases/reference.py
leanrl/taxonomy/__init__.py
leanrl/taxonomy/schema.py
leanrl/utils/__init__.py
leanrl/utils/href.py
leanrl-0.1.5.dist-info/METADATA
leanrl-0.1.5.dist-info/WHEEL
leanrl-0.1.5.dist-info/RECORD
